MANIFEST.in
README.md
setup.py
redis_funnel/__init__.py
redis_funnel/benchmark.py
redis_funnel/distributed.py
redis_funnel/funnel.lua
redis_funnel/local.py
redis_funnel.egg-info/PKG-INFO
redis_funnel.egg-info/SOURCES.txt
redis_funnel.egg-info/dependency_links.txt
redis_funnel.egg-info/requires.txt
redis_funnel.egg-info/top_level.txt
redis_funnel/mgmt/__init__.py
redis_funnel/mgmt/app.py
redis_funnel/mgmt/config.py
redis_funnel/mgmt/utils/__init__.py
redis_funnel/mgmt/utils/code.py
redis_funnel/mgmt/utils/decorator.py
redis_funnel/mgmt/utils/error.py
redis_funnel/mgmt/utils/session.py
redis_funnel/mgmt/utils/vo.py
redis_funnel/test/__init__.py
redis_funnel/test/distributed_test.py
redis_funnel/test/local_test.py