Metadata-Version: 2.1
Name: redis-funnel
Version: 0.0.1
Summary: A distributed funnel system based on redis, management system included.
Home-page: https://github.com/PurpleSun/redis_funnel
Author: fanwei.zeng
Author-email: stayblank@gmail.com
License: MIT License
Keywords: distributed,funnel,redis
Platform: any
